{
  "vaultName": "Vault",
  "lastExport": 1733383524659,
  "pluginVersion": "1.8.01",
  "validBodyClasses": "publish css-settings-manager theme-dark show-ribbon",
  "useCustomHeadContent": false,
  "useCustomFavicon": false,
  "files": [
    "00 - Index/00 - MAIN PAGE.md",
    "00 - Index/00 - Vault Remake.md",
    "00 - Index/01 - How this works.md",
    "00 - Index/02 - Why I made this folder.md",
    "00 - Index/03 - To whoever reads this.md",
    "01 - Japanese/01 - Flashcards/Japanese - Flashcards - Unit 1.md",
    "01 - Japanese/00 - Japanese INDEX.md",
    "02 - Coding & Software/01 - Projects/Python - DANTE.md",
    "02 - Coding & Software/03 - Coding Languages/01 - Python/01 - Modules/Python - Custom Modules - Expenses.md",
    "02 - Coding & Software/00 - Coding INDEX.md",
    "03 - School/00 - School INDEX.md",
    "04 - Games/01 - Devil May Cry/01 - Devil May Cry 5/DMC5 - Devil Breakers.md",
    "04 - Games/01 - Devil May Cry/01 - Devil May Cry 5/DMC5 - Mechanics.md",
    "04 - Games/04 - DBL/2024 Festival/DBL - Festival Events 2024.md",
    "04 - Games/04 - DBL/01 - DBL - Teams.md",
    "04 - Games/04 - DBL/02 - DBL - Characters.md",
    "04 - Games/00 - Games INDEX.md",
    "05 - Literature/00 - Literature INDEX.md",
    "99 - Meta/00 - Templates/(TEMPLATE) Daily.md",
    "99 - Meta/00 - Templates/(TEMPLATE) Daily (Vanilla).md",
    "99 - Meta/00 - Templates/(TEMPLATE) Unique.md",
    "99 - Meta/Preloaded Classes/202401211512 Notebook CSS Classes.md",
    "99 - Meta/Preloaded Classes/202403091325 General Tweaks CSS Classes.md",
    "lib/scripts/graph-wasm.wasm",
    "lib/fonts/94f2f163d4b698242fef.otf",
    "lib/fonts/72505e6a122c6acd5471.woff2",
    "lib/fonts/2d5198822ab091ce4305.woff2",
    "lib/fonts/c8ba52b05a9ef10f4758.woff2",
    "lib/fonts/cb10ffd7684cd9836a05.woff2",
    "lib/fonts/b5f0f109bc88052d4000.woff2",
    "lib/fonts/cbe0ae49c52c920fd563.woff2",
    "lib/fonts/535a6cf662596b3bd6a6.woff2",
    "lib/fonts/70cc7ff27245e82ad414.ttf",
    "lib/fonts/454577c22304619db035.ttf",
    "lib/fonts/52ac8f3034507f1d9e53.ttf",
    "lib/fonts/05b618077343fbbd92b7.ttf",
    "lib/fonts/4bb6ac751d1c5478ff3a.woff2",
    "lib/media/874d8b8e340f75575caa.svg",
    "lib/html/file-tree.html",
    "lib/scripts/webpage.js",
    "lib/scripts/graph-view.js",
    "lib/scripts/graph-wasm.js",
    "lib/scripts/graph-render-worker.js",
    "lib/scripts/tinycolor.js",
    "lib/scripts/pixi.js",
    "lib/scripts/minisearch.js",
    "lib/media/favicon.png",
    "lib/scripts/graph-data.js",
    "lib/styles/obsidian.css",
    "lib/styles/theme.css",
    "lib/styles/global-variable-styles.css",
    "lib/styles/main-styles.css",
    "lib/styles/snippets.css"
  ],
  "mainDependencies": [
    "lib/scripts/graph-wasm.wasm",
    "lib/fonts/94f2f163d4b698242fef.otf",
    "lib/fonts/72505e6a122c6acd5471.woff2",
    "lib/fonts/2d5198822ab091ce4305.woff2",
    "lib/fonts/c8ba52b05a9ef10f4758.woff2",
    "lib/fonts/cb10ffd7684cd9836a05.woff2",
    "lib/fonts/b5f0f109bc88052d4000.woff2",
    "lib/fonts/cbe0ae49c52c920fd563.woff2",
    "lib/fonts/535a6cf662596b3bd6a6.woff2",
    "lib/fonts/70cc7ff27245e82ad414.ttf",
    "lib/fonts/454577c22304619db035.ttf",
    "lib/fonts/52ac8f3034507f1d9e53.ttf",
    "lib/fonts/05b618077343fbbd92b7.ttf",
    "lib/fonts/4bb6ac751d1c5478ff3a.woff2",
    "lib/media/874d8b8e340f75575caa.svg",
    "lib/html/file-tree.html",
    "lib/scripts/webpage.js",
    "lib/scripts/graph-view.js",
    "lib/scripts/graph-wasm.js",
    "lib/scripts/graph-render-worker.js",
    "lib/scripts/tinycolor.js",
    "lib/scripts/pixi.js",
    "lib/scripts/minisearch.js",
    "lib/media/favicon.png",
    "lib/scripts/graph-data.js",
    "lib/styles/obsidian.css",
    "lib/styles/theme.css",
    "lib/styles/global-variable-styles.css",
    "lib/styles/main-styles.css",
    "lib/styles/snippets.css"
  ],
  "fileInfo": {
    "00 - Index/00 - MAIN PAGE.md": {
      "modifiedTime": 1733383155451,
      "sourceSize": 773,
      "exportedPath": "00-index/00-main-page.html",
      "dependencies": []
    },
    "00 - Index/00 - Vault Remake.md": {
      "modifiedTime": 1733383155451,
      "sourceSize": 650,
      "exportedPath": "00-index/00-vault-remake.html",
      "dependencies": []
    },
    "00 - Index/01 - How this works.md": {
      "modifiedTime": 1733383155451,
      "sourceSize": 1017,
      "exportedPath": "00-index/01-how-this-works.html",
      "dependencies": []
    },
    "00 - Index/02 - Why I made this folder.md": {
      "modifiedTime": 1733383155451,
      "sourceSize": 1668,
      "exportedPath": "00-index/02-why-i-made-this-folder.html",
      "dependencies": []
    },
    "00 - Index/03 - To whoever reads this.md": {
      "modifiedTime": 1733383155451,
      "sourceSize": 881,
      "exportedPath": "00-index/03-to-whoever-reads-this.html",
      "dependencies": []
    },
    "01 - Japanese/01 - Flashcards/Japanese - Flashcards - Unit 1.md": {
      "modifiedTime": 1733383155451,
      "sourceSize": 831,
      "exportedPath": "01-japanese/01-flashcards/japanese-flashcards-unit-1.html",
      "dependencies": []
    },
    "01 - Japanese/00 - Japanese INDEX.md": {
      "modifiedTime": 1733383155451,
      "sourceSize": 157,
      "exportedPath": "01-japanese/00-japanese-index.html",
      "dependencies": []
    },
    "02 - Coding & Software/01 - Projects/Python - DANTE.md": {
      "modifiedTime": 1733383155451,
      "sourceSize": 632,
      "exportedPath": "02-coding-&-software/01-projects/python-dante.html",
      "dependencies": []
    },
    "02 - Coding & Software/03 - Coding Languages/01 - Python/01 - Modules/Python - Custom Modules - Expenses.md": {
      "modifiedTime": 1733383155451,
      "sourceSize": 385,
      "exportedPath": "02-coding-&-software/03-coding-languages/01-python/01-modules/python-custom-modules-expenses.html",
      "dependencies": []
    },
    "02 - Coding & Software/00 - Coding INDEX.md": {
      "modifiedTime": 1733383155451,
      "sourceSize": 179,
      "exportedPath": "02-coding-&-software/00-coding-index.html",
      "dependencies": []
    },
    "03 - School/00 - School INDEX.md": {
      "modifiedTime": 1733383155451,
      "sourceSize": 156,
      "exportedPath": "03-school/00-school-index.html",
      "dependencies": []
    },
    "04 - Games/01 - Devil May Cry/01 - Devil May Cry 5/DMC5 - Devil Breakers.md": {
      "modifiedTime": 1733383155451,
      "sourceSize": 121,
      "exportedPath": "04-games/01-devil-may-cry/01-devil-may-cry-5/dmc5-devil-breakers.html",
      "dependencies": []
    },
    "04 - Games/01 - Devil May Cry/01 - Devil May Cry 5/DMC5 - Mechanics.md": {
      "modifiedTime": 1733383155451,
      "sourceSize": 11062,
      "exportedPath": "04-games/01-devil-may-cry/01-devil-may-cry-5/dmc5-mechanics.html",
      "dependencies": []
    },
    "04 - Games/04 - DBL/2024 Festival/DBL - Festival Events 2024.md": {
      "modifiedTime": 1733383155451,
      "sourceSize": 167,
      "exportedPath": "04-games/04-dbl/2024-festival/dbl-festival-events-2024.html",
      "dependencies": []
    },
    "04 - Games/04 - DBL/01 - DBL - Teams.md": {
      "modifiedTime": 1733383155451,
      "sourceSize": 39,
      "exportedPath": "04-games/04-dbl/01-dbl-teams.html",
      "dependencies": []
    },
    "04 - Games/04 - DBL/02 - DBL - Characters.md": {
      "modifiedTime": 1733383155451,
      "sourceSize": 39,
      "exportedPath": "04-games/04-dbl/02-dbl-characters.html",
      "dependencies": []
    },
    "04 - Games/00 - Games INDEX.md": {
      "modifiedTime": 1733383155451,
      "sourceSize": 155,
      "exportedPath": "04-games/00-games-index.html",
      "dependencies": []
    },
    "05 - Literature/00 - Literature INDEX.md": {
      "modifiedTime": 1733383155451,
      "sourceSize": 160,
      "exportedPath": "05-literature/00-literature-index.html",
      "dependencies": []
    },
    "99 - Meta/00 - Templates/(TEMPLATE) Daily.md": {
      "modifiedTime": 1733383155451,
      "sourceSize": 582,
      "exportedPath": "99-meta/00-templates/(template)-daily.html",
      "dependencies": []
    },
    "99 - Meta/00 - Templates/(TEMPLATE) Daily (Vanilla).md": {
      "modifiedTime": 1733383155451,
      "sourceSize": 201,
      "exportedPath": "99-meta/00-templates/(template)-daily-(vanilla).html",
      "dependencies": []
    },
    "99 - Meta/00 - Templates/(TEMPLATE) Unique.md": {
      "modifiedTime": 1733383155451,
      "sourceSize": 40,
      "exportedPath": "99-meta/00-templates/(template)-unique.html",
      "dependencies": []
    },
    "99 - Meta/Preloaded Classes/202401211512 Notebook CSS Classes.md": {
      "modifiedTime": 1733383155451,
      "sourceSize": 417,
      "exportedPath": "99-meta/preloaded-classes/202401211512-notebook-css-classes.html",
      "dependencies": []
    },
    "99 - Meta/Preloaded Classes/202403091325 General Tweaks CSS Classes.md": {
      "modifiedTime": 1733383155451,
      "sourceSize": 214,
      "exportedPath": "99-meta/preloaded-classes/202403091325-general-tweaks-css-classes.html",
      "dependencies": []
    },
    "lib/scripts/graph-wasm.wasm": {
      "modifiedTime": 1733383524659,
      "sourceSize": 23377,
      "exportedPath": "lib/scripts/graph-wasm.wasm",
      "dependencies": []
    },
    "lib/fonts/94f2f163d4b698242fef.otf": {
      "modifiedTime": 1733383524659,
      "sourceSize": 66800,
      "exportedPath": "lib/fonts/94f2f163d4b698242fef.otf",
      "dependencies": []
    },
    "lib/fonts/72505e6a122c6acd5471.woff2": {
      "modifiedTime": 1733383524659,
      "sourceSize": 104232,
      "exportedPath": "lib/fonts/72505e6a122c6acd5471.woff2",
      "dependencies": []
    },
    "lib/fonts/2d5198822ab091ce4305.woff2": {
      "modifiedTime": 1733383524659,
      "sourceSize": 104332,
      "exportedPath": "lib/fonts/2d5198822ab091ce4305.woff2",
      "dependencies": []
    },
    "lib/fonts/c8ba52b05a9ef10f4758.woff2": {
      "modifiedTime": 1733383524659,
      "sourceSize": 98868,
      "exportedPath": "lib/fonts/c8ba52b05a9ef10f4758.woff2",
      "dependencies": []
    },
    "lib/fonts/cb10ffd7684cd9836a05.woff2": {
      "modifiedTime": 1733383524659,
      "sourceSize": 106876,
      "exportedPath": "lib/fonts/cb10ffd7684cd9836a05.woff2",
      "dependencies": []
    },
    "lib/fonts/b5f0f109bc88052d4000.woff2": {
      "modifiedTime": 1733383524659,
      "sourceSize": 105804,
      "exportedPath": "lib/fonts/b5f0f109bc88052d4000.woff2",
      "dependencies": []
    },
    "lib/fonts/cbe0ae49c52c920fd563.woff2": {
      "modifiedTime": 1733383524659,
      "sourceSize": 106108,
      "exportedPath": "lib/fonts/cbe0ae49c52c920fd563.woff2",
      "dependencies": []
    },
    "lib/fonts/535a6cf662596b3bd6a6.woff2": {
      "modifiedTime": 1733383524659,
      "sourceSize": 111708,
      "exportedPath": "lib/fonts/535a6cf662596b3bd6a6.woff2",
      "dependencies": []
    },
    "lib/fonts/70cc7ff27245e82ad414.ttf": {
      "modifiedTime": 1733383524659,
      "sourceSize": 192740,
      "exportedPath": "lib/fonts/70cc7ff27245e82ad414.ttf",
      "dependencies": []
    },
    "lib/fonts/454577c22304619db035.ttf": {
      "modifiedTime": 1733383524659,
      "sourceSize": 161376,
      "exportedPath": "lib/fonts/454577c22304619db035.ttf",
      "dependencies": []
    },
    "lib/fonts/52ac8f3034507f1d9e53.ttf": {
      "modifiedTime": 1733383524659,
      "sourceSize": 191568,
      "exportedPath": "lib/fonts/52ac8f3034507f1d9e53.ttf",
      "dependencies": []
    },
    "lib/fonts/05b618077343fbbd92b7.ttf": {
      "modifiedTime": 1733383524659,
      "sourceSize": 155288,
      "exportedPath": "lib/fonts/05b618077343fbbd92b7.ttf",
      "dependencies": []
    },
    "lib/fonts/4bb6ac751d1c5478ff3a.woff2": {
      "modifiedTime": 1733383524659,
      "sourceSize": 7876,
      "exportedPath": "lib/fonts/4bb6ac751d1c5478ff3a.woff2",
      "dependencies": []
    },
    "lib/media/874d8b8e340f75575caa.svg": {
      "modifiedTime": 1733383524659,
      "sourceSize": 317,
      "exportedPath": "lib/media/874d8b8e340f75575caa.svg",
      "dependencies": []
    },
    "lib/html/file-tree.html": {
      "modifiedTime": 1733383524659,
      "sourceSize": 20404,
      "exportedPath": "lib/html/file-tree.html",
      "dependencies": []
    },
    "lib/scripts/webpage.js": {
      "modifiedTime": 1733383524659,
      "sourceSize": 47290,
      "exportedPath": "lib/scripts/webpage.js",
      "dependencies": []
    },
    "lib/scripts/graph-view.js": {
      "modifiedTime": 1733383524659,
      "sourceSize": 15519,
      "exportedPath": "lib/scripts/graph-view.js",
      "dependencies": []
    },
    "lib/scripts/graph-wasm.js": {
      "modifiedTime": 1733383524659,
      "sourceSize": 14021,
      "exportedPath": "lib/scripts/graph-wasm.js",
      "dependencies": []
    },
    "lib/scripts/graph-render-worker.js": {
      "modifiedTime": 1733383524659,
      "sourceSize": 5179,
      "exportedPath": "lib/scripts/graph-render-worker.js",
      "dependencies": []
    },
    "lib/scripts/tinycolor.js": {
      "modifiedTime": 1733383524659,
      "sourceSize": 29832,
      "exportedPath": "lib/scripts/tinycolor.js",
      "dependencies": []
    },
    "lib/scripts/pixi.js": {
      "modifiedTime": 1733383524659,
      "sourceSize": 449509,
      "exportedPath": "lib/scripts/pixi.js",
      "dependencies": []
    },
    "lib/scripts/minisearch.js": {
      "modifiedTime": 1733383524659,
      "sourceSize": 29422,
      "exportedPath": "lib/scripts/minisearch.js",
      "dependencies": []
    },
    "lib/media/favicon.png": {
      "modifiedTime": 1733383524659,
      "sourceSize": 1105,
      "exportedPath": "lib/media/favicon.png",
      "dependencies": []
    },
    "lib/scripts/graph-data.js": {
      "modifiedTime": 1733383524659,
      "sourceSize": 2194,
      "exportedPath": "lib/scripts/graph-data.js",
      "dependencies": []
    },
    "lib/styles/obsidian.css": {
      "modifiedTime": 1733383524659,
      "sourceSize": 131021,
      "exportedPath": "lib/styles/obsidian.css",
      "dependencies": []
    },
    "lib/styles/theme.css": {
      "modifiedTime": 1733383524659,
      "sourceSize": 459,
      "exportedPath": "lib/styles/theme.css",
      "dependencies": []
    },
    "lib/styles/global-variable-styles.css": {
      "modifiedTime": 1733383524659,
      "sourceSize": 628,
      "exportedPath": "lib/styles/global-variable-styles.css",
      "dependencies": []
    },
    "lib/styles/main-styles.css": {
      "modifiedTime": 1733383524659,
      "sourceSize": 23130,
      "exportedPath": "lib/styles/main-styles.css",
      "dependencies": []
    },
    "lib/styles/snippets.css": {
      "modifiedTime": 1733383524659,
      "sourceSize": 29636,
      "exportedPath": "lib/styles/snippets.css",
      "dependencies": []
    }
  }
}